unreal/__init__.py
unreal-0.1.1.dist-info/LICENSE
unreal-0.1.1.dist-info/METADATA
unreal-0.1.1.dist-info/WHEEL
unreal-0.1.1.dist-info/top_level.txt
unreal-0.1.1.dist-info/RECORD
